yaclipy/__about__.py
yaclipy/__init__.py
yaclipy/arg_spec.py
yaclipy/command.py
yaclipy/config.py
yaclipy/docs.py
yaclipy/exceptions.py
yaclipy-1.2.1.dist-info/METADATA
yaclipy-1.2.1.dist-info/WHEEL
yaclipy-1.2.1.dist-info/licenses/LICENSE.txt
yaclipy-1.2.1.dist-info/RECORD
