Metadata-Version: 2.1
Name: yaclipy
Version: 1.2.1
Summary: Yet another python command-line interface that has a consistent way to call any kind of function/method from the command line.
Project-URL: Documentation, https://github.com/aaron-fl/yaclipy#readme
Project-URL: Issues, https://github.com/aaron-fl/yaclipy/issues
Project-URL: Source, https://github.com/aaron-fl/yaclipy
Author-email: Aaron <aaron@framelunch.jp>
License-Expression: MIT
License-File: LICENSE.txt
Classifier: Development Status :: 4 - Beta
Classifier: Environment :: Console
Classifier: Framework :: AsyncIO
Classifier: Intended Audience :: Developers
Classifier: Programming Language :: Python
Classifier: Programming Language :: Python :: 3.7
Classifier: Programming Language :: Python :: 3.8
Classifier: Programming Language :: Python :: 3.9
Classifier: Programming Language :: Python :: 3.10
Classifier: Programming Language :: Python :: 3.11
Classifier: Programming Language :: Python :: Implementation :: CPython
Classifier: Programming Language :: Python :: Implementation :: PyPy
Classifier: Topic :: Software Development
Classifier: Topic :: Software Development :: Build Tools
Classifier: Topic :: Software Development :: User Interfaces
Classifier: Topic :: Terminals
Requires-Python: >=3.7
Requires-Dist: docstring-parser
Requires-Dist: print-ext>=2.1.1
